discover_feature_relationships/__init__.py
discover_feature_relationships/discover.py
discover_feature_relationships-1.0.3.dist-info/LICENSE
discover_feature_relationships-1.0.3.dist-info/METADATA
discover_feature_relationships-1.0.3.dist-info/WHEEL
discover_feature_relationships-1.0.3.dist-info/top_level.txt
discover_feature_relationships-1.0.3.dist-info/RECORD
